bytecode/__init__.py
bytecode/bytecode.py
bytecode/cfg.py
bytecode/concrete.py
bytecode/flags.py
bytecode/instr.py
bytecode/py.typed
bytecode/utils.py
bytecode/version.py
bytecode-0.16.0.dist-info/COPYING
bytecode-0.16.0.dist-info/METADATA
bytecode-0.16.0.dist-info/WHEEL
bytecode-0.16.0.dist-info/top_level.txt
bytecode-0.16.0.dist-info/RECORD
