Metadata-Version: 2.1
Name: bytecode
Version: 0.16.0
Summary: Python module to generate and modify bytecode
Author-email: Victor Stinner <victor.stinner@gmail.com>
Maintainer-email: "Matthieu C. Dartiailh" <m.dartiailh@gmail.com>
License: The MIT License (MIT)
Project-URL: homepage, https://github.com/MatthieuDartiailh/bytecode
Project-URL: documentation, https://bytecode.readthedocs.io/en/latest/
Project-URL: repository, https://github.com/MatthieuDartiailh/bytecode
Project-URL: changelog, https://github.com/MatthieuDartiailh/bytecode/blob/main/doc/changelog.rst
Classifier: Development Status :: 4 - Beta
Classifier: Intended Audience :: Developers
Classifier: License :: OSI Approved :: MIT License
Classifier: Natural Language :: English
Classifier: Operating System :: OS Independent
Classifier: Programming Language :: Python :: 3
Classifier: Programming Language :: Python :: 3.8
Classifier: Programming Language :: Python :: 3.9
Classifier: Programming Language :: Python :: 3.10
Classifier: Programming Language :: Python :: 3.11
Classifier: Programming Language :: Python :: 3.12
Classifier: Programming Language :: Python :: 3.13
Classifier: Topic :: Software Development :: Libraries :: Python Modules
Requires-Python: >=3.8
License-File: COPYING
Requires-Dist: typing_extensions; python_version < "3.10"
